build_scenarist/__init__.py
build_scenarist/config.py
build_scenarist/info.py
build_scenarist/runner.py
build_scenarist/scenario_help_utils.py
build_scenarist/utility.py
build_scenarist-1.0.5.data/scripts/scenarist.py
build_scenarist-1.0.5.dist-info/LICENSE.md
build_scenarist-1.0.5.dist-info/METADATA
build_scenarist-1.0.5.dist-info/WHEEL
build_scenarist-1.0.5.dist-info/top_level.txt
build_scenarist-1.0.5.dist-info/zip-safe
build_scenarist-1.0.5.dist-info/RECORD
